free_sms_otp/__init__.py
free_sms_otp/main_func.py
free_sms_otp-1.0.0.dist-info/LICENSE
free_sms_otp-1.0.0.dist-info/METADATA
free_sms_otp-1.0.0.dist-info/WHEEL
free_sms_otp-1.0.0.dist-info/top_level.txt
free_sms_otp-1.0.0.dist-info/RECORD
